zippy_form/__init__.py
zippy_form/models.py
zippy_form/serializers.py
zippy_form/urls.py
zippy_form/utils.py
zippy_form/validation_rule.py
zippy_form/validation_rule_schema.py
zippy_form/views.py
django_zippy_form-1.0.0.dist-info/METADATA
django_zippy_form-1.0.0.dist-info/WHEEL
django_zippy_form-1.0.0.dist-info/top_level.txt
django_zippy_form-1.0.0.dist-info/RECORD
